kdatagen/__init__.py
kdatagen/py.typed
kdatagen-0.0.1.dist-info/LICENSE
kdatagen-0.0.1.dist-info/METADATA
kdatagen-0.0.1.dist-info/WHEEL
kdatagen-0.0.1.dist-info/top_level.txt
kdatagen-0.0.1.dist-info/RECORD
