Metadata-Version: 2.1
Name: kdatagen
Version: 0.0.1
Summary: The kdatagen project
Home-page: https://github.com/kscalelabs/kdatagen
Author: K-Scale Labs
Requires-Python: >=3.11
License-File: LICENSE
Requires-Dist: kinfer
Requires-Dist: krec
Provides-Extra: dev
Requires-Dist: black; extra == "dev"
Requires-Dist: darglint; extra == "dev"
Requires-Dist: mypy; extra == "dev"
Requires-Dist: pytest; extra == "dev"
Requires-Dist: ruff; extra == "dev"
